bigbang/__init__.py
bigbang/archive.py
bigbang/bigbang_io.py
bigbang/cli.py
bigbang/config.py
bigbang/config.yml
bigbang/data_types.py
bigbang/icann_certificate.pem
bigbang/parse.py
bigbang/utils.py
bigbang/w3c_scrape_test.py
bigbang/analysis/3GPP_standards_release_dates.csv
bigbang/analysis/__init__.py
bigbang/analysis/affiliation.py
bigbang/analysis/attendance.py
bigbang/analysis/datatracker.py
bigbang/analysis/entity_recognition.py
bigbang/analysis/entity_resolution.py
bigbang/analysis/graph.py
bigbang/analysis/influence.py
bigbang/analysis/listserv.py
bigbang/analysis/process.py
bigbang/analysis/repo_loader.py
bigbang/analysis/thread.py
bigbang/analysis/twopeople.py
bigbang/analysis/utils.py
bigbang/datasets/__init__.py
bigbang/datasets/domains/Create Domain-Category Data.ipynb
bigbang/datasets/domains/__init__.py
bigbang/datasets/domains/domain_categories.csv
bigbang/datasets/domains/domains.py
bigbang/datasets/organizations/__init__.py
bigbang/datasets/organizations/organization_categories.csv
bigbang/datasets/organizations/organization_categories_metadata.md
bigbang/datasets/organizations/organizations.py
bigbang/ingress/__init__.py
bigbang/ingress/abstract.py
bigbang/ingress/git_repo.py
bigbang/ingress/listserv.py
bigbang/ingress/mailman.py
bigbang/ingress/pipermail.py
bigbang/ingress/utils.py
bigbang/ingress/w3c.py
bigbang/visualisation/__init__.py
bigbang/visualisation/graphs.py
bigbang/visualisation/lines.py
bigbang/visualisation/plot.py
bigbang/visualisation/stackedareachart.py
bigbang/visualisation/utils.py
bigbang_py-0.6.1.dist-info/licenses/LICENSE
bigbang_py-0.6.1.dist-info/METADATA
bigbang_py-0.6.1.dist-info/WHEEL
bigbang_py-0.6.1.dist-info/entry_points.txt
bigbang_py-0.6.1.dist-info/top_level.txt
bigbang_py-0.6.1.dist-info/RECORD
