Metadata-Version: 2.4
Name: bigbang-py
Version: 0.6.1
Summary: BigBang is a toolkit for studying communications data from collaborative projects. It currently supports analyzing mailing lists from Sourceforge, Mailman, ListServ, or .mbox files.
Author-email: BigBang Team <bigbang-dev@data-activism.net>
License:             Copyright (c) 2020 Sebastian Benthal, Nick Doty, Davide Beraldo, Niels ten Oever
Project-URL: Homepage, https://github.com/datactive/bigbang
Project-URL: Bug Tracker, https://github.com/datactive/bigbang/issues
Classifier: Programming Language :: Python :: 3
Classifier: License :: OSI Approved :: MIT License
Classifier: Operating System :: OS Independent
Requires-Python: >=3.12
License-File: LICENSE
Requires-Dist: numpy
Requires-Dist: networkx
Requires-Dist: requests
Requires-Dist: pandas
Requires-Dist: beautifulsoup4
Requires-Dist: chardet
Requires-Dist: html2text
Requires-Dist: python-dateutil
Requires-Dist: pytz
Requires-Dist: tqdm
Requires-Dist: pyyaml
Requires-Dist: certifi
Requires-Dist: levenshtein
Requires-Dist: ietfdata
Requires-Dist: python-docx
Requires-Dist: GitPython
Requires-Dist: nbformat
Requires-Dist: validator-collection
Requires-Dist: markdown
Requires-Dist: matplotlib
Requires-Dist: spacy
Requires-Dist: transformers[torch]
Requires-Dist: contractions
Requires-Dist: email_reply_parser
Requires-Dist: notebook
Requires-Dist: click
Requires-Dist: testfixtures
Provides-Extra: test
Requires-Dist: pytest; extra == "test"
Requires-Dist: coverage; extra == "test"
Requires-Dist: testfixtures; extra == "test"
Provides-Extra: dev
Requires-Dist: bigbang-py[test]; extra == "dev"
Requires-Dist: black; extra == "dev"
Requires-Dist: isort; extra == "dev"
Requires-Dist: pre-commit; extra == "dev"
Dynamic: license-file
